streamlit_cognito_auth/__init__.py
streamlit_cognito_auth/auth.py
streamlit_cognito_auth/exceptions.py
streamlit_cognito_auth/session_provider.py
streamlit_cognito_auth/utils.py
streamlit_cognito_auth_v2-1.0.2.dist-info/LICENSE
streamlit_cognito_auth_v2-1.0.2.dist-info/METADATA
streamlit_cognito_auth_v2-1.0.2.dist-info/WHEEL
streamlit_cognito_auth_v2-1.0.2.dist-info/top_level.txt
streamlit_cognito_auth_v2-1.0.2.dist-info/RECORD
