Metadata-Version: 2.1
Name: streamlit-cognito-auth-v2
Version: 1.0.2
Summary: A Streamlit component for authenticating users with AWS Cognito
Home-page: https://github.com/jbackofe/streamlit-cognito-auth.git
Author: Jared Backofen
Author-email: backofen.jared@gmail.com
Classifier: Programming Language :: Python :: 3
Classifier: License :: OSI Approved :: MIT License
Classifier: Operating System :: OS Independent
License-File: LICENSE
Requires-Dist: boto3 >=1.26.52
Requires-Dist: pycognito >=2022.12.0
Requires-Dist: pydantic <2.0.0
Requires-Dist: requests >=2.31.0
Requires-Dist: streamlit >=1.27.0
Requires-Dist: extra-streamlit-components >=0.1.56
